morecvutils/__init__.py
morecvutils/calcOptFlow.py
morecvutils/connectedComponents.py
morecvutils/cv2draw.py
morecvutils/getaviprop.py
morecvutils/lineClipping.py
morecvutils-0.9.2.dist-info/DESCRIPTION.rst
morecvutils-0.9.2.dist-info/METADATA
morecvutils-0.9.2.dist-info/RECORD
morecvutils-0.9.2.dist-info/WHEEL
morecvutils-0.9.2.dist-info/metadata.json
morecvutils-0.9.2.dist-info/top_level.txt
