Metadata-Version: 2.0
Name: morecvutils
Version: 0.9.2
Summary: Computer Vision utilities, Cohen-Sutherland line clipping, OpenCV plot helpers for Optical Flow and Blob Analysis, AVI codec helpers
Home-page: https://github.com/scivision/morecvutils
Author: Michael Hirsch, Ph.D.
Author-email: UNKNOWN
License: UNKNOWN
Platform: UNKNOWN
Classifier: Intended Audience :: Science/Research
Classifier: Development Status :: 4 - Beta
Classifier: License :: OSI Approved :: MIT License
Classifier: Topic :: Scientific/Engineering :: Visualization
Classifier: Programming Language :: Python :: 3
Requires-Python: >=3.5
Requires-Dist: imageio
Requires-Dist: numpy
Provides-Extra: cv2
Requires-Dist: cv2; extra == 'cv2'
Provides-Extra: tests
Requires-Dist: coveralls; extra == 'tests'
Requires-Dist: nose; extra == 'tests'
